tanoshi/__init__.py
tanoshi/application.py
tanoshi/exception_handlers.py
tanoshi/fglobals.py
tanoshi/requests.py
tanoshi/responses.py
tanoshi/shortcuts.py
tanoshi-0.0.1a0.dist-info/METADATA
tanoshi-0.0.1a0.dist-info/WHEEL
tanoshi-0.0.1a0.dist-info/top_level.txt
tanoshi-0.0.1a0.dist-info/RECORD
