Metadata-Version: 2.1
Name: tanoshi
Version: 0.0.1a0
Summary: A fast, asyncio based web-framework, that you'll enjoy using.
Home-page: https://github.com/justanotherbyte/tanoshi
Author: justanotherbyte
License: BSD
Project-URL: Documentation, https://tanoshi.readthedocs.io/en/latest/
Project-URL: Issue tracker, https://github.com/justanotherbyte/tanoshi/issues
Platform: UNKNOWN
Classifier: Development Status :: 3 - Alpha
Classifier: License :: OSI Approved :: BSD License
Classifier: Intended Audience :: Developers
Classifier: Natural Language :: English
Classifier: Operating System :: OS Independent
Classifier: Programming Language :: Python :: 3.8
Classifier: Programming Language :: Python :: 3.9
Classifier: Topic :: Internet
Classifier: Topic :: Software Development :: Libraries
Classifier: Topic :: Software Development :: Libraries :: Python Modules
Classifier: Topic :: Utilities
Classifier: Typing :: Typed
Requires-Python: >=3.8.0
Requires-Dist: starlette (==0.17.1)
Requires-Dist: itsdangerous (==2.0.1)
Requires-Dist: Jinja2 (==3.0.3)
